ezdvm/__init__.py
ezdvm/ezdvm.py
ezdvm-0.1.2.dist-info/LICENSE
ezdvm-0.1.2.dist-info/METADATA
ezdvm-0.1.2.dist-info/WHEEL
ezdvm-0.1.2.dist-info/top_level.txt
ezdvm-0.1.2.dist-info/RECORD
