Metadata-Version: 2.1
Name: ezdvm
Version: 0.1.2
Summary: A simple python Data Vending Machine (DVM) implementation on nostr
Author-email: Dustin Dannenhauer <dustin@dvmdash.live>
Project-URL: Homepage, https://github.com/dtdannen/ezdvm
Project-URL: Bug Tracker, https://github.com/dtdannen/ezdvm/issues
Classifier: Development Status :: 3 - Alpha
Classifier: Intended Audience :: Developers
Classifier: License :: OSI Approved :: MIT License
Classifier: Programming Language :: Python :: 3.12
Requires-Python: >=3.12
License-File: LICENSE
Requires-Dist: nostr-sdk
Requires-Dist: loguru
Requires-Dist: python-dotenv
